open_answerx-2.0.3-py3.8-nspkg.pth
akamai/edgegrid/__init__.py
akamai/edgegrid/edgegrid.py
akamai/edgegrid/edgerc.py
akamai/edgegrid/test/__init__.py
akamai/edgegrid/test/test_edgegrid.py
open_answerx-2.0.3.data/scripts/open-answerx.py
open_answerx-2.0.3.dist-info/LICENSE.txt
open_answerx-2.0.3.dist-info/METADATA
open_answerx-2.0.3.dist-info/WHEEL
open_answerx-2.0.3.dist-info/namespace_packages.txt
open_answerx-2.0.3.dist-info/top_level.txt
open_answerx-2.0.3.dist-info/RECORD
