Metadata-Version: 2.1
Name: open-answerx
Version: 2.0.3
Summary: {OPEN} client for AnswerX Cloud and Managed
Home-page: https://github.com/dxiri/OAT
Author: Diego Xirinachs
Author-email: dxirinac@akamai.com
License: LICENSE.txt
Platform: UNKNOWN
Requires-Python: >=3.4
Requires-Dist: edgegrid-python
Requires-Dist: requests
